Spyffness/Beam.py
Spyffness/Frame.py
Spyffness/Material.py
Spyffness/Node.py
Spyffness/Visualization.py
Spyffness/__init__.py
Spyffness/_version.py
Spyffness-0.1.2.dist-info/LICENSE
Spyffness-0.1.2.dist-info/METADATA
Spyffness-0.1.2.dist-info/WHEEL
Spyffness-0.1.2.dist-info/top_level.txt
Spyffness-0.1.2.dist-info/RECORD
