Metadata-Version: 2.2
Name: Spyffness
Version: 0.1.2
Summary: A Python library for structural analysis
Home-page: https://github.com/panallax/Spyffness
Author: Alex Bernadí
License: MIT
Classifier: Programming Language :: Python :: 3
Classifier: License :: OSI Approved :: MIT License
Classifier: Operating System :: OS Independent
Requires-Python: >=3.6
License-File: LICENSE
Requires-Dist: numpy>=1.20.0
Requires-Dist: scipy>=1.6.0
Requires-Dist: networkx
Dynamic: home-page
Dynamic: requires-python
